utest/__init__.py
utest/utest.py
utest-py/__init__.py
utest-py/utest.py
utest_py-0.1.0.dist-info/METADATA
utest_py-0.1.0.dist-info/WHEEL
utest_py-0.1.0.dist-info/top_level.txt
utest_py-0.1.0.dist-info/RECORD
