Metadata-Version: 2.1
Name: utest-py
Version: 0.1.0
Summary: A simple unit testing library with Halo spinners
Home-page: https://github.com/0x00ASTRA/utest
Author: ASTRÆUS
Author-email: 0x00ASTRA@proton.me
License: UNKNOWN
Platform: UNKNOWN
Requires-Dist: halo
